[
  {
    "id": 1,
    "identifier": "no-route",
    "title": "404 Not Found 1",
    "contentPreview": "<div data-content-type=\"html\" data-appearance=\"default\" data-element=\"main\">\r&lt;div class=\"page-ti"
  },
  {
    "id": 2,
    "identifier": "home-page",
    "title": "Home page",
    "contentPreview": "<div class=\"page-title\"><h2>Home Page</h2></div>"
  },
  {
    "id": 3,
    "identifier": "about-avgear",
    "title": "About AVGear",
    "contentPreview": "<div class=\"avgearshop-cms-main\">\r<p>Established in 2008, AVGear is a Canadian based company operat"
  },
  {
    "id": 4,
    "identifier": "customer-service",
    "title": "Customer Service",
    "contentPreview": "<div class=\"avgearshop-cms-main\">\r<ul class=\"questions-section\">\r    <li><a href=\"#answer1\">Shippi"
  },
  {
    "id": 5,
    "identifier": "enable-cookies",
    "title": "Enable Cookies",
    "contentPreview": "<div class=\"avgearshop-cms-main\">\r    <div class=\"page messages\">\r        <div role=\"alert\" class="
  },
  {
    "id": 6,
    "identifier": "privacy-policy",
    "title": "Privacy Policy",
    "contentPreview": "<div class=\"avgearshop-cms-main\">\r<p>\r    This privacy policy sets out how {{config path=\"general/"
  },
  {
    "id": 11,
    "identifier": "home3",
    "title": "AVGearShop",
    "contentPreview": "<div data-content-type=\"html\" data-appearance=\"default\" data-element=\"main\">&lt;div class=\"alo alo-n"
  },
  {
    "id": 12,
    "identifier": "contact-us",
    "title": "Contact Us",
    "contentPreview": "<ul class=\"disc\">\r\t<li><a href=\"#answer1\">Shipping &amp; Delivery</a></li>\r\t<li><a href=\"#answer2\""
  },
  {
    "id": 13,
    "identifier": "avgearshop-reviews",
    "title": "AVGearShop Reviews",
    "contentPreview": "<div data-content-type=\"html\" data-appearance=\"default\" data-element=\"main\">&lt;div class=\"avgearsho"
  },
  {
    "id": 14,
    "identifier": "e-transfer",
    "title": "E-Transfer",
    "contentPreview": "<div class=\"avgearshop-cms-main\">\r<p>*At this time, E-Transfers payments are for Canadian customers"
  },
  {
    "id": 15,
    "identifier": "boost-industries-sts-dr35-sit-to-stand-desk-riser",
    "title": "Boost Industries STS-DR35 Sit to Stand Desk Riser",
    "contentPreview": "<div class=\"avgearshop-cms-main\">\r<div class=\"cms-video\">\r<iframe width=\"560\" height=\"315\" src=\"ht"
  },
  {
    "id": 16,
    "identifier": "bulk-order-contact-form",
    "title": "Bulk Order Contact Form",
    "contentPreview": "<div class=\"bulk-order-main\">\r\t<div class=\"bulk-order-top-section\">\r\t\t<p>The catalogue of Boost In"
  },
  {
    "id": 17,
    "identifier": "faq-for-sts-dr35",
    "title": "FAQ for STS-DR35",
    "contentPreview": "<div class=\"avgearshop-cms-main\">\r<p><strong> Click to return to Product Page - </strong><a href=\"h"
  },
  {
    "id": 18,
    "identifier": "faq-for-sts-dr27",
    "title": "FAQ for STS-DR27",
    "contentPreview": "<div class=\"avgearshop-cms-main\">\r<p><strong> Click to return to Product Page - </strong><a href=\"h"
  },
  {
    "id": 19,
    "identifier": "faq-for-sts-dr35ii",
    "title": "FAQ for STS-DR35ii",
    "contentPreview": "<div class=\"avgearshop-cms-main\">\r<p><strong> Click to return to Product Page - </strong><a href=\"h"
  },
  {
    "id": 20,
    "identifier": "shipping-policy",
    "title": "Shipping Policy",
    "contentPreview": "<div data-content-type=\"html\" data-appearance=\"default\" data-element=\"main\">&lt;h3&gt;&lt;b&gt;Shipp"
  },
  {
    "id": 21,
    "identifier": "terms-of-service",
    "title": "Terms of Service",
    "contentPreview": "<div data-content-type=\"html\" data-appearance=\"default\" data-element=\"main\">&lt;h3&gt;&lt;b&gt;1. Ac"
  },
  {
    "id": 22,
    "identifier": "return-refund-policy",
    "title": "Return & Refund Policy",
    "contentPreview": "<div data-content-type=\"html\" data-appearance=\"default\" data-element=\"main\">&lt;h3&gt;&lt;b&gt;Retur"
  },
  {
    "id": 23,
    "identifier": "contact-thank-you",
    "title": "contact thank you",
    "contentPreview": "<div data-content-type=\"html\" data-appearance=\"default\" data-element=\"main\">&lt;p&gt;Thanks for cont"
  },
  {
    "id": 24,
    "identifier": "payment-with-affirm",
    "title": "Payment with Affirm",
    "contentPreview": "<style>#html-body [data-pb-style=XLP54EB]{justify-content:flex-start;display:flex;flex-direction:col"
  },
  {
    "id": 25,
    "identifier": "homepage-new",
    "title": "Homepage-New",
    "contentPreview": "<style>#html-body [data-pb-style=EA1XBQW]{justify-content:flex-start;display:flex;flex-direction:col"
  },
  {
    "id": 26,
    "identifier": "contact-us",
    "title": "Contact-Us",
    "contentPreview": "<div data-content-type=\"html\" data-appearance=\"default\" data-element=\"main\">&lt;ul class=\"disc\"&gt;\r"
  }
]